date_corrector/DateCorrector.py
date_corrector/__init__.py
date_corrector/helpers/DateAuxiliary.py
date_corrector/helpers/Suggestion.py
date_corrector/helpers/__init__.py
date_corrector-0.0.3.dist-info/METADATA
date_corrector-0.0.3.dist-info/WHEEL
date_corrector-0.0.3.dist-info/licenses/LICENSE
date_corrector-0.0.3.dist-info/RECORD
