Metadata-Version: 2.1
Name: date-corrector
Version: 0.0.3
Summary: A simple package for date correction
Author-email: Adham Abdelmaksoud <adham.5050@hotmail.com>
License-File: LICENSE
Classifier: License :: OSI Approved :: MIT License
Classifier: Operating System :: OS Independent
Classifier: Programming Language :: Python :: 3
Requires-Python: >=3.7
